readyplot/__init__.py
readyplot/bar_plotter.py
readyplot/base_plotter.py
readyplot/boxwhisker_plotter.py
readyplot/hist_plotter.py
readyplot/line_plotter.py
readyplot/scatter_plotter.py
readyplot/strip_plotter.py
readyplot/subplots.py
readyplot/utils.py
readyplot-1.4.18.dist-info/licenses/LICENSE
readyplot-1.4.18.dist-info/METADATA
readyplot-1.4.18.dist-info/WHEEL
readyplot-1.4.18.dist-info/top_level.txt
readyplot-1.4.18.dist-info/RECORD
