Metadata-Version: 2.4
Name: readyplot
Version: 1.4.18
Summary: Publication-ready data visualization
Author-email: Shawn Pavey <113555084+shawnpavey@users.noreply.github.com>
License: MIT
Project-URL: Homepage, https://github.com/shawnpavey/readyplot
Classifier: Programming Language :: Python :: 3
Classifier: License :: Public Domain
Classifier: Operating System :: POSIX :: Linux
Requires-Python: >=3.6
License-File: LICENSE
Requires-Dist: matplotlib
Requires-Dist: numpy
Requires-Dist: pandas
Requires-Dist: seaborn
Requires-Dist: scipy
Requires-Dist: pathlib
Requires-Dist: setuptools
Dynamic: license-file
